booth8/booth8.v
module booth8 (
    input  wire              clk,
    input  wire              rst,
    input  wire              start,
    input  wire signed [7:0] multiplicand,
    input  wire signed [7:0] multiplier,
    output reg  signed [15:0] product,
    output reg               done
);

    // Internal registers
    reg signed [15:0] A;     // Accumulator (16-bit)
    reg signed [7:0]  Q;     // Multiplier register
    reg signed [7:0]  M;     // Multiplicand register
    reg               Q_1;   // Previous LSB
    reg [3:0]         count; // 8 iterations
    reg               busy;

    // Temporary combined register (25-bit)
    reg signed [24:0] temp;

    always @(posedge clk or posedge rst) begin
        if (rst) begin
            A       <= 16'sd0;
            Q       <= 8'sd0;
            M       <= 8'sd0;
            Q_1     <= 1'b0;
            count   <= 4'd0;
            busy    <= 1'b0;
            done    <= 1'b0;
            product <= 16'sd0;
        end 
        else begin

            // Start operation
            if (start && !busy) begin
                A     <= 16'sd0;
                Q     <= multiplier;
                M     <= multiplicand;
                Q_1   <= 1'b0;
                count <= 4'd8;
                busy  <= 1'b1;
                done  <= 1'b0;
            end

            // Booth iteration
            else if (busy) begin

                // Booth decision
                case ({Q[0], Q_1})
                    2'b01: temp = {A + {{8{M[7]}}, M}, Q, Q_1};
                    2'b10: temp = {A - {{8{M[7]}}, M}, Q, Q_1};
                    default: temp = {A, Q, Q_1};
                endcase

                // Arithmetic right shift
                temp = temp >>> 1;

                // Update registers
                A   <= temp[24:9];
                Q   <= temp[8:1];
                Q_1 <= temp[0];

                count <= count - 1;

                if (count == 1) begin
                    product <= {temp[24:9], temp[8:1]};
                    busy    <= 1'b0;
                    done    <= 1'b1;
                end
            end

            else begin
                done <= 1'b0;
            end
        end
    end

endmodule

booth8/tb_booth8.v
`timescale 1ns/1ps

module tb_booth8;

    reg clk;
    reg rst;
    reg start;
    reg signed [7:0] multiplicand;
    reg signed [7:0] multiplier;

    wire signed [15:0] product;
    wire done;

    booth8 uut (
        .clk(clk),
        .rst(rst),
        .start(start),
        .multiplicand(multiplicand),
        .multiplier(multiplier),
        .product(product),
        .done(done)
    );

    // Clock generation
    always #5 clk = ~clk;

    initial begin
        $dumpfile("booth8.vcd");
        $dumpvars(0, tb_booth8);

        clk = 0;
        rst = 1;
        start = 0;
        #10 rst = 0;

        // Test 1
        multiplicand = 7;
        multiplier   = -3;
        start = 1; #10 start = 0;

        wait(done);
        $display("7 * -3 = %d", product);

        #20;

        // Test 2
        multiplicand = -8;
        multiplier   = -4;
        start = 1; #10 start = 0;

        wait(done);
        $display("-8 * -4 = %d", product);

        #20 $finish;
    end

endmodule

booth8/booth8.vcd
$date
	Sat Feb 14 03:16:14 2026
$end
$version
	Icarus Verilog
$end
$timescale
	1ps
$end
$scope module tb_booth8 $end
$var wire 16 ! product [15:0] $end
$var wire 1 " done $end
$var reg 1 # clk $end
$var reg 8 $ multiplicand [7:0] $end
$var reg 8 % multiplier [7:0] $end
$var reg 1 & rst $end
$var reg 1 ' start $end
$scope module uut $end
$var wire 1 # clk $end
$var wire 8 ( multiplicand [7:0] $end
$var wire 8 ) multiplier [7:0] $end
$var wire 1 & rst $end
$var wire 1 ' start $end
$var reg 16 * A [15:0] $end
$var reg 8 + M [7:0] $end
$var reg 8 , Q [7:0] $end
$var reg 1 - Q_1 $end
$var reg 1 . busy $end
$var reg 4 / count [3:0] $end
$var reg 1 " done $end
$var reg 16 0 product [15:0] $end
$var reg 25 1 temp [24:0] $end
$upscope $end
$upscope $end
$enddefinitions $end
#0
$dumpvars
bx 1
b0 0
b0 /
0.
0-
b0 ,
b0 +
b0 *
bx )
bx (
0'
1&
bx %
bx $
0#
0"
b0 !
$end
#5000
1#
#10000
0#
1'
b11111101 %
b11111101 )
b111 $
b111 (
0&
#15000
1.
b1000 /
b111 +
b11111101 ,
1#
#20000
0#
0'
#25000
b111 /
1-
b11111110 ,
b1111111111111100 *
b1111111111111100111111101 1
1#
#30000
0#
#35000
b110 /
0-
b11111111 ,
b1 *
b1111111110 1
1#
#40000
0#
#45000
b101 /
1-
b1111111 ,
b1111111111111101 *
b1111111111111101011111111 1
1#
#50000
0#
#55000
b100 /
b10111111 ,
b1111111111111110 *
b1111111111111110101111111 1
1#
#60000
0#
#65000
b11 /
b1011111 ,
b1111111111111111 *
b1111111111111111010111111 1
1#
#70000
0#
#75000
b10 /
b10101111 ,
b1111111111111111101011111 1
1#
#80000
0#
#85000
b1 /
b11010111 ,
b1111111111111111110101111 1
1#
#90000
0#
#95000
1"
0.
b1111111111101011 !
b1111111111101011 0
b0 /
b11101011 ,
b1111111111111111111010111 1
1#
#100000
0#
#105000
0"
1#
#110000
0#
#115000
1.
b1000 /
0-
b11111000 +
b11111100 ,
b0 *
1#
1'
b11111100 %
b11111100 )
b11111000 $
b11111000 (
#120000
0#
#125000
b111 /
b1111110 ,
b11111100 1
1#
0'
#130000
0#
#135000
b110 /
b111111 ,
b1111110 1
1#
#140000
0#
#145000
b101 /
1-
b11111 ,
b100 *
b100000111111 1
1#
#150000
0#
#155000
b100 /
b1111 ,
b10 *
b10000011111 1
1#
#160000
0#
#165000
b11 /
b111 ,
b1 *
b1000001111 1
1#
#170000
0#
#175000
b10 /
b10000011 ,
b0 *
b100000111 1
1#
#180000
0#
#185000
b1 /
b1000001 ,
b10000011 1
1#
#190000
0#
#195000
1"
0.
b100000 !
b100000 0
b0 /
b100000 ,
b1000001 1
1#
#200000
0#
#205000
0"
1#
